MGP_SDK/__init__.py
MGP_SDK/interface.py
MGP_SDK/process.py
MGP_SDK/OGC_Spec/__init__.py
MGP_SDK/OGC_Spec/interface.py
MGP_SDK/OGC_Spec/wfs.py
MGP_SDK/OGC_Spec/wms.py
MGP_SDK/OGC_Spec/wmts.py
MGP_SDK/account_service/__init__.py
MGP_SDK/account_service/accounts.py
MGP_SDK/account_service/activations.py
MGP_SDK/account_service/addresses.py
MGP_SDK/account_service/interface.py
MGP_SDK/account_service/products.py
MGP_SDK/account_service/rate_tables.py
MGP_SDK/account_service/roles.py
MGP_SDK/account_service/usage.py
MGP_SDK/account_service/users.py
MGP_SDK/analytics_service/__init__.py
MGP_SDK/analytics_service/analytics.py
MGP_SDK/analytics_service/interface.py
MGP_SDK/auth/__init__.py
MGP_SDK/auth/auth.py
MGP_SDK/basemap_service/__init__.py
MGP_SDK/basemap_service/interface.py
MGP_SDK/cli_commands/cli_commands.py
MGP_SDK/discovery_service/__init__.py
MGP_SDK/discovery_service/catalogs.py
MGP_SDK/discovery_service/collections.py
MGP_SDK/discovery_service/interface.py
MGP_SDK/discovery_service/search.py
MGP_SDK/discovery_service/server_checks.py
MGP_SDK/monitor_service/__init__.py
MGP_SDK/monitor_service/interface.py
MGP_SDK/monitor_service/monitoring.py
MGP_SDK/ordering_service/__init__.py
MGP_SDK/ordering_service/interface.py
MGP_SDK/ordering_service/orders.py
MGP_SDK/ordering_service/pipelines.py
MGP_SDK/streaming/__init__.py
MGP_SDK/streaming/interface.py
MGP_SDK/streaming/wcs_archive.py
MGP_SDK/tasking_service/__init__.py
MGP_SDK/tasking_service/interface.py
MGP_SDK/tasking_service/tasking.py
MGP_SDK/three_d/__init__.py
MGP_SDK/three_d/interface.py
MGP_SDK/three_d/three_d.py
MGP_SDK/token_service/__init__.py
MGP_SDK/token_service/token.py
MGP_SDK/usage_service/__init__.py
MGP_SDK/usage_service/interface.py
MGP_SDK/usage_service/usage.py
MGP_SDK-1.3.2.dist-info/METADATA
MGP_SDK-1.3.2.dist-info/WHEEL
MGP_SDK-1.3.2.dist-info/entry_points.txt
MGP_SDK-1.3.2.dist-info/top_level.txt
MGP_SDK-1.3.2.dist-info/RECORD
